Metadata-Version: 2.1
Name: pysortcsv
Version: 0.0.1
Summary: Learning by oattao123
Home-page: https://github.com/oattao123/pysortcsv
Download-URL: https://github.com/oattao123/pysortcsv/archive/refs/tags/v0.0.1.zip
Author: oattao123
Author-email: dceriythrrmkic@gmail.com
License: MIT
Keywords: py,sort,csv
Classifier: Development Status :: 3 - Alpha
Classifier: Intended Audience :: Education
Classifier: Topic :: Software Development :: Build Tools
Classifier: License :: OSI Approved :: MIT License
Classifier: Programming Language :: Python :: 3
Classifier: Programming Language :: Python :: 3.4
Classifier: Programming Language :: Python :: 3.5
Classifier: Programming Language :: Python :: 3.6
Classifier: Programming Language :: Python :: 3.7
Classifier: Programming Language :: Python :: 3.8
Classifier: Programming Language :: Python :: 3.9
License-File: LICENSE
License-File: LICENSE.txt
